FreezeLibs/__init__.py
FreezeLibs/FreezeLibs.py
freezelibs-1.0.1.dist-info/entry_points.txt
freezelibs-1.0.1.dist-info/LICENSE
freezelibs-1.0.1.dist-info/METADATA
freezelibs-1.0.1.dist-info/WHEEL
freezelibs-1.0.1.dist-info/RECORD
