Metadata-Version: 2.3
Name: FreezeLibs
Version: 1.0.1
Summary: A tool to extract and save Python library imports.
License: MIT
Author: Ali Abedi Madiseh
Author-email: aam7596@gmail.com
Requires-Python: >=3.11,<4.0
Classifier: License :: OSI Approved :: MIT License
Classifier: Programming Language :: Python :: 3
Classifier: Programming Language :: Python :: 3.11
Classifier: Programming Language :: Python :: 3.12
Classifier: Programming Language :: Python :: 3.13
